[
  {
    "name": "org.kie.baaas.ccp.api.DecisionRequestSpec",
    "allDeclaredConstructors": true,
    "allPublicConstructors": true,
    "allDeclaredMethods": true,
    "allPublicMethods": true,
    "allDeclaredClasses": true,
    "allPublicClasses": true
  },
  {
    "name": "org.kie.baaas.ccp.api.DecisionSpec",
    "allDeclaredConstructors": true,
    "allPublicConstructors": true,
    "allDeclaredMethods": true,
    "allPublicMethods": true,
    "allDeclaredClasses": true,
    "allPublicClasses": true
  },
  {
    "name": "org.kie.baaas.ccp.api.DecisionVersionSpec",
    "allDeclaredConstructors": true,
    "allPublicConstructors": true,
    "allDeclaredMethods": true,
    "allPublicMethods": true,
    "allDeclaredClasses": true,
    "allPublicClasses": true
  },
  {
    "name": "org.kie.baaas.ccp.api.DecisionVersionStatus",
    "allDeclaredConstructors": true,
    "allPublicConstructors": true,
    "allDeclaredMethods": true,
    "allPublicMethods": true,
    "allDeclaredClasses": true,
    "allPublicClasses": true
  },
  {
    "name": "org.kie.baaas.ccp.api.DecisionStatus",
    "allDeclaredConstructors": true,
    "allPublicConstructors": true,
    "allDeclaredMethods": true,
    "allPublicMethods": true,
    "allDeclaredClasses": true,
    "allPublicClasses": true
  },
  {
    "name": "org.kie.baaas.ccp.api.DecisionRequestStatus",
    "allDeclaredConstructors": true,
    "allPublicConstructors": true,
    "allDeclaredMethods": true,
    "allPublicMethods": true,
    "allDeclaredClasses": true,
    "allPublicClasses": true
  },
  {
    "name": "org.kie.baaas.ccp.api.Webhook",
    "allDeclaredConstructors": true,
    "allPublicConstructors": true,
    "allDeclaredMethods": true,
    "allPublicMethods": true,
    "allDeclaredClasses": true,
    "allPublicClasses": true
  },
  {
    "name": "org.kie.baaas.ccp.api.DecisionVersionRef",
    "allDeclaredConstructors": true,
    "allPublicConstructors": true,
    "allDeclaredMethods": true,
    "allPublicMethods": true,
    "allDeclaredClasses": true,
    "allPublicClasses": true
  },
  {
    "name": "org.kie.baaas.ccp.api.Kafka",
    "allDeclaredConstructors": true,
    "allPublicConstructors": true,
    "allDeclaredMethods": true,
    "allPublicMethods": true,
    "allDeclaredClasses": true,
    "allPublicClasses": true
  },
  {
    "name": "io.fabric8.kubernetes.api.model.Status",
    "allDeclaredConstructors": true,
    "allPublicConstructors": true,
    "allDeclaredMethods": true,
    "allPublicMethods": true,
    "allDeclaredClasses": true,
    "allPublicClasses": true
  }
]